MANIFEST.in
README.md
setup.cfg
setup.py
xanthos/__init__.py
xanthos/components.py
xanthos/configurations.py
xanthos/install_supplement.py
xanthos/model.py
xanthos.egg-info/PKG-INFO
xanthos.egg-info/SOURCES.txt
xanthos.egg-info/dependency_links.txt
xanthos.egg-info/requires.txt
xanthos.egg-info/top_level.txt
xanthos/accessible/__init__.py
xanthos/accessible/accessible.py
xanthos/calibrate/__init__.py
xanthos/calibrate/calibrate_abcd.py
xanthos/data/xanthos_0p5deg_landcell_reference.csv
xanthos/data_reader/__init__.py
xanthos/data_reader/data_load.py
xanthos/data_reader/ini_reader.py
xanthos/data_writer/__init__.py
xanthos/data_writer/out_writer.py
xanthos/diagnostics/__init__.py
xanthos/diagnostics/diagnostics.py
xanthos/diagnostics/time_series.py
xanthos/drought/__init__.py
xanthos/drought/drought_stats.py
xanthos/hydropower/__init__.py
xanthos/hydropower/actual.py
xanthos/hydropower/potential.py
xanthos/pet/__init__.py
xanthos/pet/hargreaves.py
xanthos/pet/hargreaves_samani.py
xanthos/pet/penman_monteith.py
xanthos/pet/thornthwaite.py
xanthos/routing/__init__.py
xanthos/routing/mrtm.py
xanthos/runoff/__init__.py
xanthos/runoff/abcd.py
xanthos/runoff/gwam.py
xanthos/test/__init__.py
xanthos/test/test_equal_outputs.py
xanthos/test/test_hargreaves_gwam_mrtm.py
xanthos/test/test_thornthwaite.py
xanthos/utils/__init__.py
xanthos/utils/general.py
xanthos/utils/math.py