Metadata-Version: 2.1
Name: xanthos
Version: 2.4.1
Summary: A global hydrologic modeling framework
Home-page: https://github.com/JGCRI/xanthos
Author: Chris R. Vernon
Author-email: chris.vernon@pnnl.gov
License: BSD2-Simplified
Platform: UNKNOWN
Requires-Python: >=3.6
